pypi/__init__.py
pypi/get2fa.py
yapi_mcp/__init__.py
yapi_mcp/__main__.py
yapi_mcp/server.py
yapi_mcp/config/__init__.py
yapi_mcp/config/api_url.py
iss_mcp_yapi-0.1.1.dist-info/METADATA
iss_mcp_yapi-0.1.1.dist-info/WHEEL
iss_mcp_yapi-0.1.1.dist-info/entry_points.txt
iss_mcp_yapi-0.1.1.dist-info/top_level.txt
iss_mcp_yapi-0.1.1.dist-info/RECORD
