Metadata-Version: 2.4
Name: iss-mcp-yapi
Version: 0.1.1
Summary: MCP server integration for YApi.
Author-email: Your Name <you@example.com>
License: MIT
Requires-Python: >=3.9
Requires-Dist: mcp==1.13.1
Requires-Dist: requests==2.32.5
